LICENSE
README.md
setup.py
types_linq/__init__.py
types_linq/cached_enumerable.py
types_linq/enumerable.py
types_linq/enumerable.pyi
types_linq/grouping.py
types_linq/lookup.py
types_linq/more_typing.py
types_linq/ordered_enumerable.py
types_linq/ordered_enumerable.pyi
types_linq/py.typed
types_linq/types_linq_error.py
types_linq/util.py
types_linq.egg-info/PKG-INFO
types_linq.egg-info/SOURCES.txt
types_linq.egg-info/dependency_links.txt
types_linq.egg-info/not-zip-safe
types_linq.egg-info/requires.txt
types_linq.egg-info/top_level.txt
types_linq/more/__init__.py
types_linq/more/extrema_enumerable.py
types_linq/more/extrema_enumerable.pyi
types_linq/more/more_enumerable.py
types_linq/more/more_enumerable.pyi
types_linq/more/more_enums.py
types_linq/more/more_error.py