Metadata-Version: 2.1
Name: types-linq
Version: 1.2.1
Summary: Standard sequence helper methods with full typing support
Home-page: https://github.com/cleoold/types-linq
Author: cleoold
License: BSD 2-Clause License
Platform: any
Classifier: Topic :: Utilities
Classifier: Development Status :: 4 - Beta
Classifier: License :: OSI Approved :: BSD License
Classifier: Operating System :: OS Independent
Classifier: Programming Language :: Python :: 3
Classifier: Typing :: Typed
Requires-Python: >=3.7
